alibabacloud_credentials/__init__.py
alibabacloud_credentials/credentials.py
credential_sdk-0.0.3.dist-info/LICENSE
credential_sdk-0.0.3.dist-info/METADATA
credential_sdk-0.0.3.dist-info/WHEEL
credential_sdk-0.0.3.dist-info/top_level.txt
credential_sdk-0.0.3.dist-info/RECORD
